setup.py
chall_cube/Cube.py
chall_cube/__init__.py
chall_cube.egg-info/PKG-INFO
chall_cube.egg-info/SOURCES.txt
chall_cube.egg-info/dependency_links.txt
chall_cube.egg-info/not-zip-safe
chall_cube.egg-info/requires.txt
chall_cube.egg-info/top_level.txt
chall_cube/device/Accelerometer.py
chall_cube/device/Buzzer.py
chall_cube/device/__init__.py
chall_cube/face/BlankFace.py
chall_cube/face/BlinkingFace.py
chall_cube/face/BlockingFace.py
chall_cube/face/Face.py
chall_cube/face/__init__.py