Metadata-Version: 1.0
Name: chall-cube
Version: 1.0.5
Summary: Base API for RaspberryPi challenges cube.
Home-page: http://github.com/alcalyn/chall-cube
Author: Alcalyn
Author-email: doubjulien@hotmail.fr
License: AGPL-3.0
Platform: UNKNOWN
